torch_trandsforms/__init__.py
torch_trandsforms/_functional.py
torch_trandsforms/_utils.py
torch_trandsforms/base.py
torch_trandsforms/ops.py
torch_trandsforms/rotation.py
torch_trandsforms/shape.py
torch_trandsforms/structure.py
torch_trandsforms/value.py
torch_trandsforms-0.4.0.dist-info/LICENSE
torch_trandsforms-0.4.0.dist-info/METADATA
torch_trandsforms-0.4.0.dist-info/WHEEL
torch_trandsforms-0.4.0.dist-info/RECORD
