Metadata-Version: 2.1
Name: torch-trandsforms
Version: 0.4.0
Summary: A pytorch-first transform library for ND data, such as multi-channel 3D volumes
Home-page: https://github.com/alexandrainst/torch-trandsforms
License: MIT
Keywords: pytorch,transforms,torchvision,data
Author: Oliver Hjermitslev
Author-email: oliver.gyldenberg@alexandra.dk
Requires-Python: >=3.8,<4.0
Classifier: Development Status :: 3 - Alpha
Classifier: Intended Audience :: Developers
Classifier: License :: OSI Approved :: MIT License
Classifier: Operating System :: OS Independent
Classifier: Programming Language :: Python :: 3
Classifier: Programming Language :: Python :: 3.8
Classifier: Programming Language :: Python :: 3.9
Classifier: Programming Language :: Python :: 3.10
Classifier: Programming Language :: Python :: 3.11
Classifier: Topic :: Software Development :: Libraries :: Python Modules
Requires-Dist: torch (>=1.13.1)
Requires-Dist: torchvision (>=0.14.0)
Project-URL: Repository, https://github.com/alexandrainst/torch-trandsforms
